dkpkg/__init__.py
dkpkg/directory.py
tests/__init__.py
tests/test_directory.py
tests/test_dkpkg_import.py
dkpkg-2.0.4.dist-info/METADATA
dkpkg-2.0.4.dist-info/WHEEL
dkpkg-2.0.4.dist-info/top_level.txt
dkpkg-2.0.4.dist-info/RECORD
