Metadata-Version: 2.1
Name: dkpkg
Version: 2.0.4
Summary: dkpkg - standardized package structure names
Home-page: https://github.com/datakortet/dkpkg
Author: Bjorn Pettersen
Author-email: bp@datakortet.no
License: BSD
Platform: UNKNOWN
Classifier: Development Status :: 3 - Alpha
Classifier: Intended Audience :: Developers
Classifier: Natural Language :: English
Classifier: License :: OSI Approved :: BSD License
Classifier: Operating System :: OS Independent
Classifier: Programming Language :: Python
Classifier: Programming Language :: Python :: 3
Classifier: Topic :: Software Development :: Libraries
Requires-Dist: invoke
Requires-Dist: PyYAML
Requires-Dist: dkfileutils
Requires-Dist: dk-tasklib
Requires-Dist: yamldirs
